chalice/__init__.py
chalice/analyzer.py
chalice/app.py
chalice/awsclient.py
chalice/compat.py
chalice/config.py
chalice/constants.py
chalice/invoke.py
chalice/local.py
chalice/logs.py
chalice/package.py
chalice/pipeline.py
chalice/policies-extra.json
chalice/policies.json
chalice/policy.py
chalice/py.typed
chalice/test.py
chalice/utils.py
chalice/api/__init__.py
chalice/cdk/__init__.py
chalice/cdk/construct.py
chalice/cli/__init__.py
chalice/cli/factory.py
chalice/cli/newproj.py
chalice/cli/reloader.py
chalice/cli/filewatch/__init__.py
chalice/cli/filewatch/eventbased.py
chalice/cli/filewatch/stat.py
chalice/deploy/__init__.py
chalice/deploy/appgraph.py
chalice/deploy/deployer.py
chalice/deploy/executor.py
chalice/deploy/models.py
chalice/deploy/packager.py
chalice/deploy/planner.py
chalice/deploy/swagger.py
chalice/deploy/sweeper.py
chalice/deploy/validate.py
chalice/templates/0000-rest-api/.gitignore
chalice/templates/0000-rest-api/app.py
chalice/templates/0000-rest-api/metadata.json
chalice/templates/0000-rest-api/requirements-dev.txt
chalice/templates/0000-rest-api/requirements.txt
chalice/templates/0000-rest-api/.chalice/config.json
chalice/templates/0000-rest-api/chalicelib/__init__.py
chalice/templates/0000-rest-api/tests/__init__.py
chalice/templates/0000-rest-api/tests/test_app.py
chalice/templates/0002-s3-event-handler/.gitignore
chalice/templates/0002-s3-event-handler/app.py
chalice/templates/0002-s3-event-handler/metadata.json
chalice/templates/0002-s3-event-handler/requirements-dev.txt
chalice/templates/0002-s3-event-handler/requirements.txt
chalice/templates/0002-s3-event-handler/.chalice/config.json
chalice/templates/0002-s3-event-handler/chalicelib/__init__.py
chalice/templates/0002-s3-event-handler/tests/__init__.py
chalice/templates/0002-s3-event-handler/tests/test_app.py
chalice/templates/0007-lambda-only/.gitignore
chalice/templates/0007-lambda-only/app.py
chalice/templates/0007-lambda-only/metadata.json
chalice-1.31.3.dist-info/LICENSE
chalice-1.31.3.dist-info/METADATA
chalice-1.31.3.dist-info/NOTICE
chalice-1.31.3.dist-info/WHEEL
chalice-1.31.3.dist-info/entry_points.txt
chalice-1.31.3.dist-info/top_level.txt
chalice-1.31.3.dist-info/RECORD
