Metadata-Version: 2.1
Name: chalice
Version: 1.31.3
Summary: Microframework
Home-page: https://github.com/aws/chalice
Author: James Saryerwinnie
Author-email: js@jamesls.com
License: Apache License 2.0
Keywords: chalice
Classifier: Development Status :: 5 - Production/Stable
Classifier: Intended Audience :: Developers
Classifier: License :: OSI Approved :: Apache Software License
Classifier: Natural Language :: English
Classifier: Programming Language :: Python :: 3
Classifier: Programming Language :: Python :: 3.8
Classifier: Programming Language :: Python :: 3.9
Classifier: Programming Language :: Python :: 3.10
Classifier: Programming Language :: Python :: 3.11
Classifier: Programming Language :: Python :: 3.12
License-File: LICENSE
License-File: NOTICE
Requires-Dist: click<9.0,>=7
Requires-Dist: botocore<2.0.0,>=1.14.0
Requires-Dist: typing-extensions<5.0.0,>=4.0.0; python_version < "3.8"
Requires-Dist: six<2.0.0,>=1.10.0
Requires-Dist: pip<24.4,>=9
Requires-Dist: jmespath<2.0.0,>=0.9.3
Requires-Dist: pyyaml<7.0.0,>=5.3.1
Requires-Dist: inquirer<4.0.0,>=3.0.0
Requires-Dist: wheel
Requires-Dist: setuptools
Provides-Extra: event-file-poller
Requires-Dist: watchdog==2.3.1; extra == "event-file-poller"
Provides-Extra: cdk
Requires-Dist: aws_cdk.aws_iam<2.0,>=1.85.0; extra == "cdk"
Requires-Dist: aws_cdk.aws-s3-assets<2.0,>=1.85.0; extra == "cdk"
Requires-Dist: aws_cdk.cloudformation-include<2.0,>=1.85.0; extra == "cdk"
Requires-Dist: aws_cdk.core<2.0,>=1.85.0; extra == "cdk"
Provides-Extra: cdkv2
Requires-Dist: aws-cdk-lib<3.0,>2.0; extra == "cdkv2"
